{
  "type": "GROUP",
"name": "All Requests",
"path": "",
"pathFormatted": "group_missing-name--1146707516",
"stats": {
    "name": "All Requests",
    "numberOfRequests": {
        "total": 31200,
        "ok": 31200,
        "ko": 0
    },
    "minResponseTime": {
        "total": 0,
        "ok": 0,
        "ko": 0
    },
    "maxResponseTime": {
        "total": 301,
        "ok": 301,
        "ko": 0
    },
    "meanResponseTime": {
        "total": 14,
        "ok": 14,
        "ko": 0
    },
    "standardDeviation": {
        "total": 25,
        "ok": 25,
        "ko": 0
    },
    "percentiles1": {
        "total": 6,
        "ok": 6,
        "ko": 0
    },
    "percentiles2": {
        "total": 10,
        "ok": 10,
        "ko": 0
    },
    "percentiles3": {
        "total": 92,
        "ok": 92,
        "ko": 0
    },
    "percentiles4": {
        "total": 110,
        "ok": 110,
        "ko": 0
    },
    "group1": {
    "name": "t < 800 ms",
    "htmlName": "t < 800 ms",
    "count": 31200,
    "percentage": 100
},
    "group2": {
    "name": "800 ms <= t < 1200 ms",
    "htmlName": "t >= 800 ms <br> t < 1200 ms",
    "count": 0,
    "percentage": 0
},
    "group3": {
    "name": "t >= 1200 ms",
    "htmlName": "t >= 1200 ms",
    "count": 0,
    "percentage": 0
},
    "group4": {
    "name": "failed",
    "htmlName": "failed",
    "count": 0,
    "percentage": 0
},
    "meanNumberOfRequestsPerSecond": {
        "total": 421.6216216216216,
        "ok": 421.6216216216216,
        "ko": 0
    }
},
"contents": {
"req_request-0-693933696": {
        "type": "REQUEST",
        "name": "request_0",
"path": "request_0",
"pathFormatted": "req_request-0-693933696",
"stats": {
    "name": "request_0",
    "numberOfRequests": {
        "total": 1200,
        "ok": 1200,
        "ko": 0
    },
    "minResponseTime": {
        "total": 3,
        "ok": 3,
        "ko": 0
    },
    "maxResponseTime": {
        "total": 105,
        "ok": 105,
        "ko": 0
    },
    "meanResponseTime": {
        "total": 6,
        "ok": 6,
        "ko": 0
    },
    "standardDeviation": {
        "total": 5,
        "ok": 5,
        "ko": 0
    },
    "percentiles1": {
        "total": 5,
        "ok": 5,
        "ko": 0
    },
    "percentiles2": {
        "total": 6,
        "ok": 6,
        "ko": 0
    },
    "percentiles3": {
        "total": 12,
        "ok": 12,
        "ko": 0
    },
    "percentiles4": {
        "total": 22,
        "ok": 22,
        "ko": 0
    },
    "group1": {
    "name": "t < 800 ms",
    "htmlName": "t < 800 ms",
    "count": 1200,
    "percentage": 100
},
    "group2": {
    "name": "800 ms <= t < 1200 ms",
    "htmlName": "t >= 800 ms <br> t < 1200 ms",
    "count": 0,
    "percentage": 0
},
    "group3": {
    "name": "t >= 1200 ms",
    "htmlName": "t >= 1200 ms",
    "count": 0,
    "percentage": 0
},
    "group4": {
    "name": "failed",
    "htmlName": "failed",
    "count": 0,
    "percentage": 0
},
    "meanNumberOfRequestsPerSecond": {
        "total": 16.216216216216218,
        "ok": 16.216216216216218,
        "ko": 0
    }
}
    },"req_kawico-ico--775827749": {
        "type": "REQUEST",
        "name": "KaWIco.ico",
"path": "KaWIco.ico",
"pathFormatted": "req_kawico-ico--775827749",
"stats": {
    "name": "KaWIco.ico",
    "numberOfRequests": {
        "total": 6000,
        "ok": 6000,
        "ko": 0
    },
    "minResponseTime": {
        "total": 0,
        "ok": 0,
        "ko": 0
    },
    "maxResponseTime": {
        "total": 60,
        "ok": 60,
        "ko": 0
    },
    "meanResponseTime": {
        "total": 6,
        "ok": 6,
        "ko": 0
    },
    "standardDeviation": {
        "total": 4,
        "ok": 4,
        "ko": 0
    },
    "percentiles1": {
        "total": 5,
        "ok": 5,
        "ko": 0
    },
    "percentiles2": {
        "total": 7,
        "ok": 7,
        "ko": 0
    },
    "percentiles3": {
        "total": 12,
        "ok": 12,
        "ko": 0
    },
    "percentiles4": {
        "total": 18,
        "ok": 18,
        "ko": 0
    },
    "group1": {
    "name": "t < 800 ms",
    "htmlName": "t < 800 ms",
    "count": 6000,
    "percentage": 100
},
    "group2": {
    "name": "800 ms <= t < 1200 ms",
    "htmlName": "t >= 800 ms <br> t < 1200 ms",
    "count": 0,
    "percentage": 0
},
    "group3": {
    "name": "t >= 1200 ms",
    "htmlName": "t >= 1200 ms",
    "count": 0,
    "percentage": 0
},
    "group4": {
    "name": "failed",
    "htmlName": "failed",
    "count": 0,
    "percentage": 0
},
    "meanNumberOfRequestsPerSecond": {
        "total": 81.08108108108108,
        "ok": 81.08108108108108,
        "ko": 0
    }
}
    },"req_main-3212c522-j-1992062288": {
        "type": "REQUEST",
        "name": "main.3212c522.js",
"path": "main.3212c522.js",
"pathFormatted": "req_main-3212c522-j-1992062288",
"stats": {
    "name": "main.3212c522.js",
    "numberOfRequests": {
        "total": 6000,
        "ok": 6000,
        "ko": 0
    },
    "minResponseTime": {
        "total": 0,
        "ok": 0,
        "ko": 0
    },
    "maxResponseTime": {
        "total": 234,
        "ok": 234,
        "ko": 0
    },
    "meanResponseTime": {
        "total": 23,
        "ok": 23,
        "ko": 0
    },
    "standardDeviation": {
        "total": 37,
        "ok": 37,
        "ko": 0
    },
    "percentiles1": {
        "total": 6,
        "ok": 6,
        "ko": 0
    },
    "percentiles2": {
        "total": 12,
        "ok": 12,
        "ko": 0
    },
    "percentiles3": {
        "total": 102,
        "ok": 102,
        "ko": 0
    },
    "percentiles4": {
        "total": 120,
        "ok": 120,
        "ko": 0
    },
    "group1": {
    "name": "t < 800 ms",
    "htmlName": "t < 800 ms",
    "count": 6000,
    "percentage": 100
},
    "group2": {
    "name": "800 ms <= t < 1200 ms",
    "htmlName": "t >= 800 ms <br> t < 1200 ms",
    "count": 0,
    "percentage": 0
},
    "group3": {
    "name": "t >= 1200 ms",
    "htmlName": "t >= 1200 ms",
    "count": 0,
    "percentage": 0
},
    "group4": {
    "name": "failed",
    "htmlName": "failed",
    "count": 0,
    "percentage": 0
},
    "meanNumberOfRequestsPerSecond": {
        "total": 81.08108108108108,
        "ok": 81.08108108108108,
        "ko": 0
    }
}
    },"req_request-1-693933697": {
        "type": "REQUEST",
        "name": "request_1",
"path": "request_1",
"pathFormatted": "req_request-1-693933697",
"stats": {
    "name": "request_1",
    "numberOfRequests": {
        "total": 1200,
        "ok": 1200,
        "ko": 0
    },
    "minResponseTime": {
        "total": 7,
        "ok": 7,
        "ko": 0
    },
    "maxResponseTime": {
        "total": 60,
        "ok": 60,
        "ko": 0
    },
    "meanResponseTime": {
        "total": 12,
        "ok": 12,
        "ko": 0
    },
    "standardDeviation": {
        "total": 4,
        "ok": 4,
        "ko": 0
    },
    "percentiles1": {
        "total": 11,
        "ok": 11,
        "ko": 0
    },
    "percentiles2": {
        "total": 14,
        "ok": 14,
        "ko": 0
    },
    "percentiles3": {
        "total": 19,
        "ok": 19,
        "ko": 0
    },
    "percentiles4": {
        "total": 25,
        "ok": 25,
        "ko": 0
    },
    "group1": {
    "name": "t < 800 ms",
    "htmlName": "t < 800 ms",
    "count": 1200,
    "percentage": 100
},
    "group2": {
    "name": "800 ms <= t < 1200 ms",
    "htmlName": "t >= 800 ms <br> t < 1200 ms",
    "count": 0,
    "percentage": 0
},
    "group3": {
    "name": "t >= 1200 ms",
    "htmlName": "t >= 1200 ms",
    "count": 0,
    "percentage": 0
},
    "group4": {
    "name": "failed",
    "htmlName": "failed",
    "count": 0,
    "percentage": 0
},
    "meanNumberOfRequestsPerSecond": {
        "total": 16.216216216216218,
        "ok": 16.216216216216218,
        "ko": 0
    }
}
    },"req_main-a9dff72e-c-1103459944": {
        "type": "REQUEST",
        "name": "main.a9dff72e.css",
"path": "main.a9dff72e.css",
"pathFormatted": "req_main-a9dff72e-c-1103459944",
"stats": {
    "name": "main.a9dff72e.css",
    "numberOfRequests": {
        "total": 6000,
        "ok": 6000,
        "ko": 0
    },
    "minResponseTime": {
        "total": 0,
        "ok": 0,
        "ko": 0
    },
    "maxResponseTime": {
        "total": 78,
        "ok": 78,
        "ko": 0
    },
    "meanResponseTime": {
        "total": 8,
        "ok": 8,
        "ko": 0
    },
    "standardDeviation": {
        "total": 7,
        "ok": 7,
        "ko": 0
    },
    "percentiles1": {
        "total": 6,
        "ok": 6,
        "ko": 0
    },
    "percentiles2": {
        "total": 11,
        "ok": 11,
        "ko": 0
    },
    "percentiles3": {
        "total": 20,
        "ok": 20,
        "ko": 0
    },
    "percentiles4": {
        "total": 27,
        "ok": 27,
        "ko": 0
    },
    "group1": {
    "name": "t < 800 ms",
    "htmlName": "t < 800 ms",
    "count": 6000,
    "percentage": 100
},
    "group2": {
    "name": "800 ms <= t < 1200 ms",
    "htmlName": "t >= 800 ms <br> t < 1200 ms",
    "count": 0,
    "percentage": 0
},
    "group3": {
    "name": "t >= 1200 ms",
    "htmlName": "t >= 1200 ms",
    "count": 0,
    "percentage": 0
},
    "group4": {
    "name": "failed",
    "htmlName": "failed",
    "count": 0,
    "percentage": 0
},
    "meanNumberOfRequestsPerSecond": {
        "total": 81.08108108108108,
        "ok": 81.08108108108108,
        "ko": 0
    }
}
    },"req_request-2-693933698": {
        "type": "REQUEST",
        "name": "request_2",
"path": "request_2",
"pathFormatted": "req_request-2-693933698",
"stats": {
    "name": "request_2",
    "numberOfRequests": {
        "total": 1200,
        "ok": 1200,
        "ko": 0
    },
    "minResponseTime": {
        "total": 7,
        "ok": 7,
        "ko": 0
    },
    "maxResponseTime": {
        "total": 62,
        "ok": 62,
        "ko": 0
    },
    "meanResponseTime": {
        "total": 13,
        "ok": 13,
        "ko": 0
    },
    "standardDeviation": {
        "total": 5,
        "ok": 5,
        "ko": 0
    },
    "percentiles1": {
        "total": 12,
        "ok": 12,
        "ko": 0
    },
    "percentiles2": {
        "total": 15,
        "ok": 15,
        "ko": 0
    },
    "percentiles3": {
        "total": 21,
        "ok": 21,
        "ko": 0
    },
    "percentiles4": {
        "total": 27,
        "ok": 27,
        "ko": 0
    },
    "group1": {
    "name": "t < 800 ms",
    "htmlName": "t < 800 ms",
    "count": 1200,
    "percentage": 100
},
    "group2": {
    "name": "800 ms <= t < 1200 ms",
    "htmlName": "t >= 800 ms <br> t < 1200 ms",
    "count": 0,
    "percentage": 0
},
    "group3": {
    "name": "t >= 1200 ms",
    "htmlName": "t >= 1200 ms",
    "count": 0,
    "percentage": 0
},
    "group4": {
    "name": "failed",
    "htmlName": "failed",
    "count": 0,
    "percentage": 0
},
    "meanNumberOfRequestsPerSecond": {
        "total": 16.216216216216218,
        "ok": 16.216216216216218,
        "ko": 0
    }
}
    },"req_request-3-693933699": {
        "type": "REQUEST",
        "name": "request_3",
"path": "request_3",
"pathFormatted": "req_request-3-693933699",
"stats": {
    "name": "request_3",
    "numberOfRequests": {
        "total": 1200,
        "ok": 1200,
        "ko": 0
    },
    "minResponseTime": {
        "total": 5,
        "ok": 5,
        "ko": 0
    },
    "maxResponseTime": {
        "total": 64,
        "ok": 64,
        "ko": 0
    },
    "meanResponseTime": {
        "total": 11,
        "ok": 11,
        "ko": 0
    },
    "standardDeviation": {
        "total": 5,
        "ok": 5,
        "ko": 0
    },
    "percentiles1": {
        "total": 10,
        "ok": 10,
        "ko": 0
    },
    "percentiles2": {
        "total": 13,
        "ok": 13,
        "ko": 0
    },
    "percentiles3": {
        "total": 18,
        "ok": 18,
        "ko": 0
    },
    "percentiles4": {
        "total": 25,
        "ok": 25,
        "ko": 0
    },
    "group1": {
    "name": "t < 800 ms",
    "htmlName": "t < 800 ms",
    "count": 1200,
    "percentage": 100
},
    "group2": {
    "name": "800 ms <= t < 1200 ms",
    "htmlName": "t >= 800 ms <br> t < 1200 ms",
    "count": 0,
    "percentage": 0
},
    "group3": {
    "name": "t >= 1200 ms",
    "htmlName": "t >= 1200 ms",
    "count": 0,
    "percentage": 0
},
    "group4": {
    "name": "failed",
    "htmlName": "failed",
    "count": 0,
    "percentage": 0
},
    "meanNumberOfRequestsPerSecond": {
        "total": 16.216216216216218,
        "ok": 16.216216216216218,
        "ko": 0
    }
}
    },"req_request-4-693933700": {
        "type": "REQUEST",
        "name": "request_4",
"path": "request_4",
"pathFormatted": "req_request-4-693933700",
"stats": {
    "name": "request_4",
    "numberOfRequests": {
        "total": 1200,
        "ok": 1200,
        "ko": 0
    },
    "minResponseTime": {
        "total": 2,
        "ok": 2,
        "ko": 0
    },
    "maxResponseTime": {
        "total": 43,
        "ok": 43,
        "ko": 0
    },
    "meanResponseTime": {
        "total": 8,
        "ok": 8,
        "ko": 0
    },
    "standardDeviation": {
        "total": 3,
        "ok": 3,
        "ko": 0
    },
    "percentiles1": {
        "total": 7,
        "ok": 7,
        "ko": 0
    },
    "percentiles2": {
        "total": 10,
        "ok": 10,
        "ko": 0
    },
    "percentiles3": {
        "total": 14,
        "ok": 14,
        "ko": 0
    },
    "percentiles4": {
        "total": 19,
        "ok": 19,
        "ko": 0
    },
    "group1": {
    "name": "t < 800 ms",
    "htmlName": "t < 800 ms",
    "count": 1200,
    "percentage": 100
},
    "group2": {
    "name": "800 ms <= t < 1200 ms",
    "htmlName": "t >= 800 ms <br> t < 1200 ms",
    "count": 0,
    "percentage": 0
},
    "group3": {
    "name": "t >= 1200 ms",
    "htmlName": "t >= 1200 ms",
    "count": 0,
    "percentage": 0
},
    "group4": {
    "name": "failed",
    "htmlName": "failed",
    "count": 0,
    "percentage": 0
},
    "meanNumberOfRequestsPerSecond": {
        "total": 16.216216216216218,
        "ok": 16.216216216216218,
        "ko": 0
    }
}
    },"req_request-5-693933701": {
        "type": "REQUEST",
        "name": "request_5",
"path": "request_5",
"pathFormatted": "req_request-5-693933701",
"stats": {
    "name": "request_5",
    "numberOfRequests": {
        "total": 1200,
        "ok": 1200,
        "ko": 0
    },
    "minResponseTime": {
        "total": 1,
        "ok": 1,
        "ko": 0
    },
    "maxResponseTime": {
        "total": 63,
        "ok": 63,
        "ko": 0
    },
    "meanResponseTime": {
        "total": 5,
        "ok": 5,
        "ko": 0
    },
    "standardDeviation": {
        "total": 4,
        "ok": 4,
        "ko": 0
    },
    "percentiles1": {
        "total": 4,
        "ok": 4,
        "ko": 0
    },
    "percentiles2": {
        "total": 5,
        "ok": 5,
        "ko": 0
    },
    "percentiles3": {
        "total": 10,
        "ok": 10,
        "ko": 0
    },
    "percentiles4": {
        "total": 16,
        "ok": 16,
        "ko": 0
    },
    "group1": {
    "name": "t < 800 ms",
    "htmlName": "t < 800 ms",
    "count": 1200,
    "percentage": 100
},
    "group2": {
    "name": "800 ms <= t < 1200 ms",
    "htmlName": "t >= 800 ms <br> t < 1200 ms",
    "count": 0,
    "percentage": 0
},
    "group3": {
    "name": "t >= 1200 ms",
    "htmlName": "t >= 1200 ms",
    "count": 0,
    "percentage": 0
},
    "group4": {
    "name": "failed",
    "htmlName": "failed",
    "count": 0,
    "percentage": 0
},
    "meanNumberOfRequestsPerSecond": {
        "total": 16.216216216216218,
        "ok": 16.216216216216218,
        "ko": 0
    }
}
    },"req_css2-family-pop--93030034": {
        "type": "REQUEST",
        "name": "css2?family=Poppins&display=swap",
"path": "css2?family=Poppins&display=swap",
"pathFormatted": "req_css2-family-pop--93030034",
"stats": {
    "name": "css2?family=Poppins&display=swap",
    "numberOfRequests": {
        "total": 1200,
        "ok": 1200,
        "ko": 0
    },
    "minResponseTime": {
        "total": 83,
        "ok": 83,
        "ko": 0
    },
    "maxResponseTime": {
        "total": 301,
        "ok": 301,
        "ko": 0
    },
    "meanResponseTime": {
        "total": 100,
        "ok": 100,
        "ko": 0
    },
    "standardDeviation": {
        "total": 15,
        "ok": 15,
        "ko": 0
    },
    "percentiles1": {
        "total": 97,
        "ok": 97,
        "ko": 0
    },
    "percentiles2": {
        "total": 102,
        "ok": 102,
        "ko": 0
    },
    "percentiles3": {
        "total": 123,
        "ok": 123,
        "ko": 0
    },
    "percentiles4": {
        "total": 141,
        "ok": 141,
        "ko": 0
    },
    "group1": {
    "name": "t < 800 ms",
    "htmlName": "t < 800 ms",
    "count": 1200,
    "percentage": 100
},
    "group2": {
    "name": "800 ms <= t < 1200 ms",
    "htmlName": "t >= 800 ms <br> t < 1200 ms",
    "count": 0,
    "percentage": 0
},
    "group3": {
    "name": "t >= 1200 ms",
    "htmlName": "t >= 1200 ms",
    "count": 0,
    "percentage": 0
},
    "group4": {
    "name": "failed",
    "htmlName": "failed",
    "count": 0,
    "percentage": 0
},
    "meanNumberOfRequestsPerSecond": {
        "total": 16.216216216216218,
        "ok": 16.216216216216218,
        "ko": 0
    }
}
    },"req_request-6-693933702": {
        "type": "REQUEST",
        "name": "request_6",
"path": "request_6",
"pathFormatted": "req_request-6-693933702",
"stats": {
    "name": "request_6",
    "numberOfRequests": {
        "total": 1200,
        "ok": 1200,
        "ko": 0
    },
    "minResponseTime": {
        "total": 2,
        "ok": 2,
        "ko": 0
    },
    "maxResponseTime": {
        "total": 125,
        "ok": 125,
        "ko": 0
    },
    "meanResponseTime": {
        "total": 6,
        "ok": 6,
        "ko": 0
    },
    "standardDeviation": {
        "total": 6,
        "ok": 6,
        "ko": 0
    },
    "percentiles1": {
        "total": 5,
        "ok": 5,
        "ko": 0
    },
    "percentiles2": {
        "total": 7,
        "ok": 7,
        "ko": 0
    },
    "percentiles3": {
        "total": 13,
        "ok": 13,
        "ko": 0
    },
    "percentiles4": {
        "total": 22,
        "ok": 22,
        "ko": 0
    },
    "group1": {
    "name": "t < 800 ms",
    "htmlName": "t < 800 ms",
    "count": 1200,
    "percentage": 100
},
    "group2": {
    "name": "800 ms <= t < 1200 ms",
    "htmlName": "t >= 800 ms <br> t < 1200 ms",
    "count": 0,
    "percentage": 0
},
    "group3": {
    "name": "t >= 1200 ms",
    "htmlName": "t >= 1200 ms",
    "count": 0,
    "percentage": 0
},
    "group4": {
    "name": "failed",
    "htmlName": "failed",
    "count": 0,
    "percentage": 0
},
    "meanNumberOfRequestsPerSecond": {
        "total": 16.216216216216218,
        "ok": 16.216216216216218,
        "ko": 0
    }
}
    },"req_request-7-693933703": {
        "type": "REQUEST",
        "name": "request_7",
"path": "request_7",
"pathFormatted": "req_request-7-693933703",
"stats": {
    "name": "request_7",
    "numberOfRequests": {
        "total": 1200,
        "ok": 1200,
        "ko": 0
    },
    "minResponseTime": {
        "total": 2,
        "ok": 2,
        "ko": 0
    },
    "maxResponseTime": {
        "total": 110,
        "ok": 110,
        "ko": 0
    },
    "meanResponseTime": {
        "total": 6,
        "ok": 6,
        "ko": 0
    },
    "standardDeviation": {
        "total": 5,
        "ok": 5,
        "ko": 0
    },
    "percentiles1": {
        "total": 5,
        "ok": 5,
        "ko": 0
    },
    "percentiles2": {
        "total": 7,
        "ok": 7,
        "ko": 0
    },
    "percentiles3": {
        "total": 14,
        "ok": 14,
        "ko": 0
    },
    "percentiles4": {
        "total": 23,
        "ok": 23,
        "ko": 0
    },
    "group1": {
    "name": "t < 800 ms",
    "htmlName": "t < 800 ms",
    "count": 1200,
    "percentage": 100
},
    "group2": {
    "name": "800 ms <= t < 1200 ms",
    "htmlName": "t >= 800 ms <br> t < 1200 ms",
    "count": 0,
    "percentage": 0
},
    "group3": {
    "name": "t >= 1200 ms",
    "htmlName": "t >= 1200 ms",
    "count": 0,
    "percentage": 0
},
    "group4": {
    "name": "failed",
    "htmlName": "failed",
    "count": 0,
    "percentage": 0
},
    "meanNumberOfRequestsPerSecond": {
        "total": 16.216216216216218,
        "ok": 16.216216216216218,
        "ko": 0
    }
}
    },"req_request-9-693933705": {
        "type": "REQUEST",
        "name": "request_9",
"path": "request_9",
"pathFormatted": "req_request-9-693933705",
"stats": {
    "name": "request_9",
    "numberOfRequests": {
        "total": 1200,
        "ok": 1200,
        "ko": 0
    },
    "minResponseTime": {
        "total": 1,
        "ok": 1,
        "ko": 0
    },
    "maxResponseTime": {
        "total": 80,
        "ok": 80,
        "ko": 0
    },
    "meanResponseTime": {
        "total": 3,
        "ok": 3,
        "ko": 0
    },
    "standardDeviation": {
        "total": 4,
        "ok": 4,
        "ko": 0
    },
    "percentiles1": {
        "total": 2,
        "ok": 2,
        "ko": 0
    },
    "percentiles2": {
        "total": 4,
        "ok": 4,
        "ko": 0
    },
    "percentiles3": {
        "total": 8,
        "ok": 8,
        "ko": 0
    },
    "percentiles4": {
        "total": 12,
        "ok": 12,
        "ko": 0
    },
    "group1": {
    "name": "t < 800 ms",
    "htmlName": "t < 800 ms",
    "count": 1200,
    "percentage": 100
},
    "group2": {
    "name": "800 ms <= t < 1200 ms",
    "htmlName": "t >= 800 ms <br> t < 1200 ms",
    "count": 0,
    "percentage": 0
},
    "group3": {
    "name": "t >= 1200 ms",
    "htmlName": "t >= 1200 ms",
    "count": 0,
    "percentage": 0
},
    "group4": {
    "name": "failed",
    "htmlName": "failed",
    "count": 0,
    "percentage": 0
},
    "meanNumberOfRequestsPerSecond": {
        "total": 16.216216216216218,
        "ok": 16.216216216216218,
        "ko": 0
    }
}
    },"req_request-11-37108176": {
        "type": "REQUEST",
        "name": "request_11",
"path": "request_11",
"pathFormatted": "req_request-11-37108176",
"stats": {
    "name": "request_11",
    "numberOfRequests": {
        "total": 1200,
        "ok": 1200,
        "ko": 0
    },
    "minResponseTime": {
        "total": 2,
        "ok": 2,
        "ko": 0
    },
    "maxResponseTime": {
        "total": 75,
        "ok": 75,
        "ko": 0
    },
    "meanResponseTime": {
        "total": 6,
        "ok": 6,
        "ko": 0
    },
    "standardDeviation": {
        "total": 5,
        "ok": 5,
        "ko": 0
    },
    "percentiles1": {
        "total": 5,
        "ok": 5,
        "ko": 0
    },
    "percentiles2": {
        "total": 7,
        "ok": 7,
        "ko": 0
    },
    "percentiles3": {
        "total": 14,
        "ok": 14,
        "ko": 0
    },
    "percentiles4": {
        "total": 23,
        "ok": 23,
        "ko": 0
    },
    "group1": {
    "name": "t < 800 ms",
    "htmlName": "t < 800 ms",
    "count": 1200,
    "percentage": 100
},
    "group2": {
    "name": "800 ms <= t < 1200 ms",
    "htmlName": "t >= 800 ms <br> t < 1200 ms",
    "count": 0,
    "percentage": 0
},
    "group3": {
    "name": "t >= 1200 ms",
    "htmlName": "t >= 1200 ms",
    "count": 0,
    "percentage": 0
},
    "group4": {
    "name": "failed",
    "htmlName": "failed",
    "count": 0,
    "percentage": 0
},
    "meanNumberOfRequestsPerSecond": {
        "total": 16.216216216216218,
        "ok": 16.216216216216218,
        "ko": 0
    }
}
    }
}

}